main.py
hey_helper-0.1.0.dist-info/licenses/LICENSE
hey_helper-0.1.0.dist-info/METADATA
hey_helper-0.1.0.dist-info/WHEEL
hey_helper-0.1.0.dist-info/entry_points.txt
hey_helper-0.1.0.dist-info/top_level.txt
hey_helper-0.1.0.dist-info/RECORD
