Metadata-Version: 2.4
Name: hey-helper
Version: 0.1.0
Summary: Ask a question, get an answer—right in your terminal.
Home-page: https://o.eval.blog/hey
Author: Vikrant Singh Chauhan
License: MIT
Classifier: Programming Language :: Python :: 3
Classifier: License :: OSI Approved :: MIT License
Classifier: Operating System :: OS Independent
Requires-Python: >=3.8
License-File: LICENSE
Requires-Dist: click
Requires-Dist: requests
Requires-Dist: langchain
Requires-Dist: langchain-ollama
Requires-Dist: langgraph
Requires-Dist: playwright
Dynamic: author
Dynamic: classifier
Dynamic: description
Dynamic: description-content-type
Dynamic: home-page
Dynamic: license
Dynamic: license-file
Dynamic: requires-dist
Dynamic: requires-python
Dynamic: summary
